pytest_describe/__init__.py
pytest_describe/plugin.py
pytest_describe/shared.py
pytest_describe-3.1.0.dist-info/licenses/LICENSE
pytest_describe-3.1.0.dist-info/WHEEL
pytest_describe-3.1.0.dist-info/entry_points.txt
pytest_describe-3.1.0.dist-info/METADATA
pytest_describe-3.1.0.dist-info/RECORD
