Metadata-Version: 2.4
Name: pytest-describe
Version: 3.1.0
Summary: Describe-style plugin for pytest
Keywords: test,unittest,plugin,describe
Author: Robin Pedersen
Author-email: Robin Pedersen <robinpeder@gmail.com>
License-Expression: MIT
License-File: LICENSE
Classifier: Development Status :: 5 - Production/Stable
Classifier: Intended Audience :: Developers
Classifier: License :: OSI Approved :: MIT License
Classifier: Operating System :: MacOS :: MacOS X
Classifier: Operating System :: Microsoft :: Windows
Classifier: Operating System :: POSIX
Classifier: Framework :: Pytest
Classifier: Programming Language :: Python :: 3
Classifier: Programming Language :: Python :: 3 :: Only
Classifier: Programming Language :: Python :: 3.9
Classifier: Programming Language :: Python :: 3.10
Classifier: Programming Language :: Python :: 3.11
Classifier: Programming Language :: Python :: 3.12
Classifier: Programming Language :: Python :: 3.13
Classifier: Programming Language :: Python :: 3.14
Classifier: Topic :: Software Development :: Libraries
Classifier: Topic :: Software Development :: Testing
Classifier: Topic :: Utilities
Requires-Dist: pytest>=6,<10
Maintainer: Christoph Zwerschke
Maintainer-email: Christoph Zwerschke <cito@online.de>
Requires-Python: >=3.9
Project-URL: Homepage, https://github.com/pytest-dev/pytest-describe
Project-URL: Source, https://github.com/pytest-dev/pytest-describe
Project-URL: Tracker, https://github.com/pytest-dev/pytest-describe/issues
